shypan/__init__.py
shypan-0.0.2.dist-info/LICENSE
shypan-0.0.2.dist-info/METADATA
shypan-0.0.2.dist-info/WHEEL
shypan-0.0.2.dist-info/top_level.txt
shypan-0.0.2.dist-info/RECORD
