Metadata-Version: 2.1
Name: shypan
Version: 0.0.2
Summary: Librairie Shypan, développé par Panda et Shyba
Home-page: https://github.com/ShypanLib/Shypan
Author: ShypanLib
Author-email: shypanlib@gmail.com
License: UNKNOWN
Project-URL: Bug Tracker, https://github.com/ShypanLib/Shypan/issues
Platform: UNKNOWN
Classifier: Programming Language :: Python :: 3
Classifier: License :: OSI Approved :: MIT License
Classifier: Operating System :: OS Independent
Requires-Python: >=3.10
License-File: LICENSE
